flim_flam/cli.py
flim_flam/service.py
flim_flam-0.1.2.dist-info/entry_points.txt
flim_flam-0.1.2.dist-info/WHEEL
flim_flam-0.1.2.dist-info/METADATA
flim_flam-0.1.2.dist-info/RECORD
